hmrcCurrencyRate/__init__.py
hmrcCurrencyRate/hmrc.py
hmrcCurrencyRate-0.0.9.dist-info/METADATA
hmrcCurrencyRate-0.0.9.dist-info/WHEEL
hmrcCurrencyRate-0.0.9.dist-info/top_level.txt
hmrcCurrencyRate-0.0.9.dist-info/RECORD
