Metadata-Version: 2.1
Name: hmrcCurrencyRate
Version: 0.0.9
Summary: A small example package
Home-page: https://github.com/YChanHuang/hmrcCurrencyRate
Author: James Huang
Author-email: yichan.huang93@gmail.com
License: UNKNOWN
Platform: UNKNOWN
Classifier: Programming Language :: Python :: 3
Classifier: License :: OSI Approved :: MIT License
Classifier: Operating System :: OS Independent
Requires-Python: >=3.6
